pyconverters_deeptranscript/__init__.py
pyconverters_deeptranscript/deeptranscript.py
pyconverters_deeptranscript/webhook.py
pyconverters_deeptranscript-0.5.59.dist-info/entry_points.txt
pyconverters_deeptranscript-0.5.59.dist-info/LICENSE
pyconverters_deeptranscript-0.5.59.dist-info/WHEEL
pyconverters_deeptranscript-0.5.59.dist-info/METADATA
pyconverters_deeptranscript-0.5.59.dist-info/RECORD
